{"address1": "Ion House", "address2": "Dr. E. Moses Road Mahalaxmi", "city": "Mumbai", "zip": "400011", "country": "India", "phone": "91 22 6231 2000", "fax": "91 22 2493 8737", "website": "https://www.ionexchangeglobal.com", "industry": "Pollution & Treatment Controls", "industryKey": "pollution-treatment-controls", "industryDisp": "Pollution & Treatment Controls", "sector": "Industrials", "sectorKey": "industrials", "sectorDisp": "Industrials", "longBusinessSummary": "Ion Exchange (India) Limited, together with its subsidiaries, provides water and environmental management solutions in India and internationally. It operates through Engineering, Chemicals, and Consumer Products segments. The company offers raw water, process, post, and drinking water treatment; waste water, water recycling, and zero liquid discharge systems; sludge dewatering and waste to energy systems; ion exchange process, membrane process, ion exchange membrane process, and 3D modelling systems; and resin, incudes water purification equipment; and catalyst grade, adsorbent grade, chemical and special process, pharma grade, nuclear grade, hydrometallurgy, food and beverage, bio diesel, and sugar refining resins. It also provides membranes, such asnano filtration, ultra-filtration, low pressure and seawater RO, fouling resistant, and brackish resistant membranes; and specialty chemical treatment programmes, including cooling and boiler water treatment products, fireside treatment products, coagulants, flocculants, membrane cleaning chemicals, and water testing kits. In addition, the company offers INDION online controllers and transmitters, water quality monitoring instruments, water quality measuring indicators, remote monitoring systems, and online effluent monitoring systems; and consultancy, operator training, design engineering, project financing, and operations and maintenance services, as well as installation, commissioning, rehabilitation, and plant automation services. It serves automotive, cement, chemicals, electronics, food and beverage, fertilizers, paper and pulp, pharma, power, refinery and petrochemicals, steel and metallurgy, mining and minerals, sugar, and textiles industries; educational, hospitality, hospital, laboratory, railway, and defense institutions; communities and municipalities; and residential and commercial establishments industries. The company was incorporated in 1964 and is based in Mumbai, India.", "fullTimeEmployees": 2521, "companyOfficers": [{"maxAge": 1, "name": "Mr. Rajesh  Sharma B.Sc., LL.B.", "age": 71, "title": "Executive Chairman", "yearBorn": 1954, "fiscalYear": 2025, "totalPay": 75509509, "exercisedValue": 0, "unexercisedValue": 0}, {"maxAge": 1, "name": "Mr. Indraneel  Dutt", "age": 54, "title": "MD, CEO & Director", "yearBorn": 1971, "fiscalYear": 2025, "totalPay": 12945965, "exercisedValue": 0, "unexercisedValue": 0}, {"maxAge": 1, "name": "Mr. Rajesh Kumar Srivastava", "age": 57, "title": "President & CHRO", "yearBorn": 1968, "fiscalYear": 2025, "exercisedValue": 0, "unexercisedValue": 0}, {"maxAge": 1, "name": "Mr. Vasant J. Naik", "age": 59, "title": "Group Chief Financial Officer", "yearBorn": 1966, "fiscalYear": 2025, "exercisedValue": 0, "unexercisedValue": 0}, {"maxAge": 1, "name": "Mr. Ajay A. Popat", "title": "President of Corporate Diversification, Technology & Marketing", "fiscalYear": 2025, "exercisedValue": 0, "unexercisedValue": 0}, {"maxAge": 1, "name": "Ms. Nikisha Yogesh Solanki", "title": "Company Secretary & Compliance Officer", "fiscalYear": 2025, "exercisedValue": 0, "unexercisedValue": 0}, {"maxAge": 1, "name": "Shashikant S. Raut", "title": "Vice President of Projects & Sales", "fiscalYear": 2025, "exercisedValue": 0, "unexercisedValue": 0}, {"maxAge": 1, "name": "Mr. Nandkumar Manohar Ranadive", "title": "Group Head of Financial Planning & Risk Management", "fiscalYear": 2025, "totalPay": 6493619, "exercisedValue": 0, "unexercisedValue": 0}, {"maxAge": 1, "name": "Mr. S. N. Iyengar", "title": "Executive Vice President of Medium Industry Segment", "fiscalYear": 2025, "exercisedValue": 0, "unexercisedValue": 0}, {"maxAge": 1, "name": "Mr. Prashant K. Chitnis", "title": "Senior Vice President of Technology", "fiscalYear": 2025, "exercisedValue": 0, "unexercisedValue": 0}], "compensationAsOfEpochDate": 1767139200, "executiveTeam": [], "maxAge": 86400, "priceHint": 2, "previousClose": 341.95, "open": 345.0, "dayLow": 336.6, "dayHigh": 347.1, "regularMarketPreviousClose": 341.95, "regularMarketOpen": 345.0, "regularMarketDayLow": 336.6, "regularMarketDayHigh": 347.1, "dividendRate": 1.5, "dividendYield": 0.44, "exDividendDate": 1757376000, "payoutRatio": 0.097799994, "beta": 0.21, "trailingPE": 22.0228, "volume": 169747, "regularMarketVolume": 169747, "averageVolume": 287459, "averageVolume10days": 545708, "averageDailyVolume10Day": 545708, "bid": 0.0, "ask": 0.0, "marketCap": 41600311296, "nonDilutedMarketCap": 42048360422, "fiftyTwoWeekLow": 322.1, "fiftyTwoWeekHigh": 580.75, "allTimeHigh": 768.4, "allTimeLow": 148.56, "priceToSalesTrailing12Months": 1.4413881, "fiftyDayAverage": 360.376, "twoHundredDayAverage": 409.74625, "trailingAnnualDividendRate": 0.0, "trailingAnnualDividendYield": 0.0, "currency": "INR", "tradeable": false, "enterpriseValue": 40405401600, "profitMargins": 0.06302, "floatShares": 77211145, "sharesOutstanding": 122930450, "heldPercentInsiders": 0.44524, "heldPercentInstitutions": 0.19872999, "impliedSharesOutstanding": 123059647, "bookValue": 109.036, "priceToBook": 3.100352, "lastFiscalYearEnd": 1743379200, "nextFiscalYearEnd": 1774915200, "mostRecentQuarter": 1767139200, "earningsQuarterlyGrowth": -0.582, "netIncomeToCommon": 1818866048, "trailingEps": 15.35, "lastSplitFactor": "10:1", "lastSplitDate": 1686528000, "enterpriseToRevenue": 1.4, "enterpriseToEbitda": 15.375, "52WeekChange": -0.33297157, "SandP52WeekChange": 0.12811458, "lastDividendValue": 1.5, "lastDividendDate": 1756771200, "quoteType": "EQUITY", "currentPrice": 338.05, "recommendationKey": "none", "totalCash": 3907200000, "totalCashPerShare": 32.951, "ebitda": 2628057856, "totalDebt": 4206299904, "totalRevenue": 28861284352, "debtToEquity": 32.485, "revenuePerShare": 243.452, "grossProfits": 10617837568, "earningsGrowth": -0.582, "revenueGrowth": 0.064, "grossMargins": 0.36789, "ebitdaMargins": 0.09106, "operatingMargins": 0.05539, "financialCurrency": "INR", "symbol": "IONEXCHANG.NS", "language": "en-US", "region": "US", "typeDisp": "Equity", "quoteSourceName": "Delayed Quote", "triggerable": true, "customPriceAlertConfidence": "HIGH", "corporateActions": [], "regularMarketTime": 1774000796, "exchange": "NSI", "messageBoardId": "finmb_20345316", "exchangeTimezoneName": "Asia/Kolkata", "exchangeTimezoneShortName": "IST", "gmtOffSetMilliseconds": 19800000, "market": "in_market", "esgPopulated": false, "regularMarketChangePercent": -1.1405247, "regularMarketPrice": 338.05, "shortName": "ION EXCHANGE (INDIA) LTD", "longName": "Ion Exchange (India) Limited", "hasPrePostMarketData": false, "firstTradeDateMilliseconds": 1645501500000, "regularMarketChange": -3.9000244, "regularMarketDayRange": "336.6 - 347.1", "fullExchangeName": "NSE", "averageDailyVolume3Month": 287459, "fiftyTwoWeekLowChange": 15.949982, "fiftyTwoWeekLowChangePercent": 0.049518727, "fiftyTwoWeekRange": "322.1 - 580.75", "fiftyTwoWeekHighChange": -242.70001, "fiftyTwoWeekHighChangePercent": -0.4179079, "fiftyTwoWeekChangePercent": -33.297157, "earningsTimestampStart": 1753959540, "earningsTimestampEnd": 1754308800, "earningsCallTimestampStart": 1748593800, "earningsCallTimestampEnd": 1748593800, "isEarningsDateEstimate": false, "epsTrailingTwelveMonths": 15.35, "fiftyDayAverageChange": -22.32602, "fiftyDayAverageChangePercent": -0.061952014, "twoHundredDayAverageChange": -71.69626, "twoHundredDayAverageChangePercent": -0.17497721, "sourceInterval": 15, "exchangeDataDelayedBy": 15, "marketState": "CLOSED", "cryptoTradeable": false, "trailingPegRatio": null}