{"address1": "Rahejas, Main Avenue", "address2": "2nd Floor Vallabhai Patel Road Santacruz (West)", "city": "Mumbai", "zip": "400054", "country": "India", "phone": "91 22 4944 7060", "website": "https://www.prismjohnson.in", "industry": "Building Materials", "industryKey": "building-materials", "industryDisp": "Building Materials", "sector": "Basic Materials", "sectorKey": "basic-materials", "sectorDisp": "Basic Materials", "longBusinessSummary": "Prism Johnson Limited, an integrated building materials company, manufactures and sells cement, tiles, and ready-mixed concrete in India and internationally. It operates through Cement, H & R Johnson (India) (HRJ), Ready Mixed Concrete (RMC), and Insurance segments. The company offers Portland pozzolana and Ordinary Portland cement under the Champion, Champion Plus, Champion Duratech, and Champion All Weather brands. It also provides ceramic, industrial, and vitrified tiles; and sanitaryware, bath fittings, faucets, accessories, and engineered marble and quartz products under the Johnson Tiles, Johnson Marbonite, Johnson Porselano, Johnson Bathware, Johnson Endura, and Johnson International brand names. Additionally, the company offers construction chemicals and plasters. Further, it engages in the general insurance business, including health, motor, home, and office insurance products. The company was formerly known as Prism Cement Limited and changed its name to Prism Johnson Limited in April 2018. Prism Johnson Limited was incorporated in 1992 and is headquartered in Mumbai, India.", "fullTimeEmployees": 5146, "companyOfficers": [{"maxAge": 1, "name": "Mr. Vijay  Aggarwal", "age": 57, "title": "MD & Executive Non-Independent Director", "yearBorn": 1968, "exercisedValue": 0, "unexercisedValue": 0}, {"maxAge": 1, "name": "Mr. Sarat Kumar Chandak", "age": 54, "title": "CEO of HRJ Division & Executive Director", "yearBorn": 1971, "exercisedValue": 0, "unexercisedValue": 0}, {"maxAge": 1, "name": "Mr. Raakesh  Jain", "title": "CEO of Cement & Whole-Time Director", "exercisedValue": 0, "unexercisedValue": 0}, {"maxAge": 1, "name": "Mr. Arun Kumar Agarwal", "age": 53, "title": "Chief Financial Officer", "yearBorn": 1972, "exercisedValue": 0, "unexercisedValue": 0}, {"maxAge": 1, "name": "Mr. Ashish  Samal", "age": 41, "title": "Chief Investor Relations Officer", "yearBorn": 1984, "exercisedValue": 0, "unexercisedValue": 0}, {"maxAge": 1, "name": "Mr. Rajnish  Sacheti", "title": "Chief Legal Officer", "exercisedValue": 0, "unexercisedValue": 0}, {"maxAge": 1, "name": "Mr. Shailesh  Dholakia", "age": 53, "title": "Company Secretary & Compliance Officer", "yearBorn": 1972, "exercisedValue": 0, "unexercisedValue": 0}, {"maxAge": 1, "name": "Mr. Prabir Kumar Ray", "title": "Chief Human Resources Officer", "exercisedValue": 0, "unexercisedValue": 0}, {"maxAge": 1, "name": "Mr. Aditya Bob Mahendru", "title": "Chief Innovation Officer", "exercisedValue": 0, "unexercisedValue": 0}, {"maxAge": 1, "name": "Mr. .  Sanjeeva", "title": "President of Special Projects & Chief Commercial Officer", "exercisedValue": 0, "unexercisedValue": 0}], "executiveTeam": [], "maxAge": 86400, "priceHint": 2, "previousClose": 125.03, "open": 125.55, "dayLow": 125.0, "dayHigh": 125.99, "regularMarketPreviousClose": 125.03, "regularMarketOpen": 125.55, "regularMarketDayLow": 125.0, "regularMarketDayHigh": 125.99, "exDividendDate": 1565049600, "payoutRatio": 0.0, "beta": 0.445, "trailingPE": 32.141388, "forwardPE": 58.153484, "volume": 89281, "regularMarketVolume": 89281, "averageVolume": 607788, "averageVolume10days": 191451, "averageDailyVolume10Day": 191451, "bid": 0.0, "ask": 0.0, "bidSize": 0, "askSize": 0, "marketCap": 62934671360, "nonDilutedMarketCap": 62934673197, "fiftyTwoWeekLow": 114.72, "fiftyTwoWeekHigh": 176.0, "allTimeHigh": 246.0, "allTimeLow": 3.75, "priceToSalesTrailing12Months": 0.81488454, "fiftyDayAverage": 124.7674, "twoHundredDayAverage": 142.447, "trailingAnnualDividendRate": 0.0, "trailingAnnualDividendYield": 0.0, "currency": "INR", "tradeable": false, "enterpriseValue": 79880945664, "profitMargins": 0.02535, "floatShares": 210939768, "sharesOutstanding": 503356580, "heldPercentInsiders": 0.76835996, "heldPercentInstitutions": 0.08262999, "impliedSharesOutstanding": 503356580, "bookValue": 31.198, "priceToBook": 4.0076284, "lastFiscalYearEnd": 1743379200, "nextFiscalYearEnd": 1774915200, "mostRecentQuarter": 1767139200, "earningsQuarterlyGrowth": 0.27, "netIncomeToCommon": 1957699968, "trailingEps": 3.89, "forwardEps": 2.15, "enterpriseToRevenue": 1.034, "enterpriseToEbitda": 15.713, "52WeekChange": -0.027911663, "SandP52WeekChange": 0.12811458, "lastDividendValue": 1.0, "lastDividendDate": 1565049600, "quoteType": "EQUITY", "currentPrice": 125.03, "targetHighPrice": 162.0, "targetLowPrice": 130.0, "targetMeanPrice": 149.33333, "targetMedianPrice": 156.0, "recommendationKey": "none", "numberOfAnalystOpinions": 3, "totalCash": 3730599936, "totalCashPerShare": 7.386, "ebitda": 5083599872, "totalDebt": 16941800448, "totalRevenue": 77231398912, "debtToEquity": 93.47, "revenuePerShare": 153.482, "grossProfits": 33436100608, "earningsGrowth": 0.26, "revenueGrowth": -0.008, "grossMargins": 0.43293, "ebitdaMargins": 0.06582, "operatingMargins": 0.0035299999, "financialCurrency": "INR", "symbol": "PRSMJOHNSN.NS", "language": "en-US", "region": "US", "typeDisp": "Equity", "quoteSourceName": "Delayed Quote", "triggerable": true, "customPriceAlertConfidence": "HIGH", "marketState": "CLOSED", "sourceInterval": 15, "exchangeDataDelayedBy": 15, "cryptoTradeable": false, "regularMarketChange": 0.0, "regularMarketDayRange": "125.0 - 125.99", "fullExchangeName": "NSE", "averageDailyVolume3Month": 607788, "fiftyTwoWeekLowChange": 10.309998, "fiftyTwoWeekLowChangePercent": 0.08987097, "fiftyTwoWeekRange": "114.72 - 176.0", "fiftyTwoWeekHighChange": -50.97, "fiftyTwoWeekHighChangePercent": -0.28960228, "fiftyTwoWeekChangePercent": -2.7911663, "earningsTimestampStart": 1754564340, "earningsTimestampEnd": 1754913600, "isEarningsDateEstimate": true, "epsTrailingTwelveMonths": 3.89, "epsForward": 2.15, "epsCurrentYear": -0.63333, "priceEpsCurrentYear": -197.41682, "fiftyDayAverageChange": 0.26259613, "fiftyDayAverageChangePercent": 0.0021046854, "twoHundredDayAverageChange": -17.417007, "twoHundredDayAverageChangePercent": -0.122270085, "exchange": "NSI", "messageBoardId": "finmb_882659", "exchangeTimezoneName": "Asia/Kolkata", "exchangeTimezoneShortName": "IST", "gmtOffSetMilliseconds": 19800000, "market": "in_market", "esgPopulated": false, "regularMarketChangePercent": 0.0, "regularMarketPrice": 125.03, "shortName": "PRISM JOHNSON LIMITED", "longName": "Prism Johnson Limited", "corporateActions": [], "regularMarketTime": 1774000797, "hasPrePostMarketData": false, "firstTradeDateMilliseconds": 1025495100000, "trailingPegRatio": null}