{"address1": "Paras Twin Towers", "address2": "Tower-B, 10th Floor Sector-54 Golf Course Road", "city": "Gurugram", "zip": "122002", "country": "India", "phone": "91 12 4478 4530", "website": "https://www.federalmogulgoetzeindia.net", "industry": "Auto Parts", "industryKey": "auto-parts", "industryDisp": "Auto Parts", "sector": "Consumer Cyclical", "sectorKey": "consumer-cyclical", "sectorDisp": "Consumer Cyclical", "longBusinessSummary": "Federal-Mogul Goetze (India) Limited manufactures, supply, and distributes automotive components for two/three/four-wheeler automobiles in India and internationally. It provides pistons, piston rings, and wet and dry cylinder liners for a range of applications, including bi-wheelers, passenger cars, SUVs, tractors, light and heavy commercial vehicles, locomotive engines, stationary engines, and high output locomotive diesel engines. The company also offers sintered metal products for various engines and automotive applications, such as valve trains, transmission, lubrication pumps, and other engine/structural parts. It exports its products. The company was formerly known as Goetze (India) Limited and changed its name to Federal-Mogul Goetze (India) Limited in 2006. The company was incorporated in 1954 and is based in Gurugram, India. Federal-Mogul Goetze (India) Limited is a subsidiary of Federal Mogul Holding Limited.", "fullTimeEmployees": 2599, "companyOfficers": [{"maxAge": 1, "name": "Dr. Khalid Iqbal Khan", "age": 57, "title": "Whole Time Director of Legal, Compliance Officer, Company Secretary & Director", "yearBorn": 1968, "fiscalYear": 2025, "totalPay": 17940681, "exercisedValue": 0, "unexercisedValue": 0}, {"maxAge": 1, "name": "Mr. Kunal  Kirti", "age": 47, "title": "Director of HR", "yearBorn": 1978, "fiscalYear": 2025, "exercisedValue": 0, "unexercisedValue": 0}, {"maxAge": 1, "name": "Mr. Rajesh Kumar Sinha B.E, MBA", "age": 55, "title": "Director of Operations and Ring & Liners-India, Campus Head", "yearBorn": 1970, "fiscalYear": 2025, "totalPay": 31408620, "exercisedValue": 0, "unexercisedValue": 0}, {"maxAge": 1, "name": "Mr. Abhishek  Nagar", "title": "Company Secretary", "fiscalYear": 2025, "exercisedValue": 0, "unexercisedValue": 0}, {"maxAge": 1, "name": "Mr. Jasbir  Singh", "title": "Executive", "fiscalYear": 2025, "exercisedValue": 0, "unexercisedValue": 0}, {"maxAge": 1, "name": "Mr. Gangasagar Neminath Hemade", "age": 53, "title": "Chief Executive Officer", "yearBorn": 1972, "fiscalYear": 2025, "exercisedValue": 0, "unexercisedValue": 0}, {"maxAge": 1, "name": "Mr. Amit  Mittal", "age": 58, "title": "MD, CFO & Director", "yearBorn": 1967, "fiscalYear": 2025, "exercisedValue": 0, "unexercisedValue": 0}, {"maxAge": 1, "name": "Mr. Sanjeev  Sharma", "age": 59, "title": "Director of Ops - Piston India, Campus Head of Patiala & Operation Head of 4 JIT Plants - India", "yearBorn": 1966, "fiscalYear": 2025, "exercisedValue": 0, "unexercisedValue": 0}, {"maxAge": 1, "name": "Mr. Varun  Dua", "title": "Additional Executive Non-Independent Director", "fiscalYear": 2025, "exercisedValue": 0, "unexercisedValue": 0}, {"maxAge": 1, "name": "Dr. Rakesh  Kumar", "title": "Executive", "fiscalYear": 2025, "exercisedValue": 0, "unexercisedValue": 0}], "compensationAsOfEpochDate": 1767139200, "executiveTeam": [], "maxAge": 86400, "priceHint": 2, "previousClose": 382.05, "open": 381.2, "dayLow": 367.8, "dayHigh": 381.25, "regularMarketPreviousClose": 382.05, "regularMarketOpen": 381.2, "regularMarketDayLow": 367.8, "regularMarketDayHigh": 381.25, "exDividendDate": 1125964800, "payoutRatio": 0.0, "beta": -0.091, "trailingPE": 11.39188, "volume": 8428, "regularMarketVolume": 8428, "averageVolume": 61287, "averageVolume10days": 62390, "averageDailyVolume10Day": 62390, "bid": 369.1, "ask": 370.95, "bidSize": 0, "askSize": 0, "marketCap": 20603359232, "nonDilutedMarketCap": 21206967956, "fiftyTwoWeekLow": 319.65, "fiftyTwoWeekHigh": 622.0, "allTimeHigh": 666.45, "allTimeLow": 17.0, "priceToSalesTrailing12Months": 1.0571167, "fiftyDayAverage": 420.367, "twoHundredDayAverage": 492.6045, "trailingAnnualDividendRate": 0.0, "trailingAnnualDividendYield": 0.0, "currency": "INR", "tradeable": false, "enterpriseValue": 15480891392, "profitMargins": 0.092819996, "floatShares": 13923465, "sharesOutstanding": 55632130, "heldPercentInsiders": 0.78132004, "heldPercentInstitutions": 0.00324, "impliedSharesOutstanding": 55632130, "bookValue": 244.48, "priceToBook": 1.5148479, "lastFiscalYearEnd": 1743379200, "nextFiscalYearEnd": 1774915200, "mostRecentQuarter": 1767139200, "earningsQuarterlyGrowth": 0.005, "netIncomeToCommon": 1809159936, "trailingEps": 32.51, "enterpriseToRevenue": 0.794, "enterpriseToEbitda": 4.464, "52WeekChange": 0.13840878, "SandP52WeekChange": 0.12811458, "lastDividendValue": 4.0, "lastDividendDate": 1125964800, "quoteType": "EQUITY", "currentPrice": 370.35, "recommendationKey": "none", "totalCash": 6569726976, "totalCashPerShare": 118.037, "ebitda": 3468214528, "totalDebt": 20562000, "totalRevenue": 19490146304, "debtToEquity": 0.143, "revenuePerShare": 350.168, "grossProfits": 12238983168, "earningsGrowth": 0.004, "revenueGrowth": 0.144, "grossMargins": 0.62796, "ebitdaMargins": 0.17795, "operatingMargins": 0.09389, "financialCurrency": "INR", "symbol": "FMGOETZE.NS", "language": "en-US", "region": "US", "typeDisp": "Equity", "quoteSourceName": "Free Realtime Quote", "triggerable": true, "customPriceAlertConfidence": "HIGH", "corporateActions": [], "regularMarketTime": 1774239319, "exchange": "NSI", "messageBoardId": "finmb_881059", "exchangeTimezoneName": "Asia/Kolkata", "exchangeTimezoneShortName": "IST", "gmtOffSetMilliseconds": 19800000, "market": "in_market", "esgPopulated": false, "regularMarketChangePercent": -3.0624218, "regularMarketPrice": 370.35, "shortName": "FEDERAL-MOGUL GOETZE (IND", "longName": "Federal-Mogul Goetze (India) Limited", "hasPrePostMarketData": false, "firstTradeDateMilliseconds": 1025495100000, "regularMarketChange": -11.699982, "regularMarketDayRange": "367.8 - 381.25", "fullExchangeName": "NSE", "averageDailyVolume3Month": 61287, "fiftyTwoWeekLowChange": 50.700012, "fiftyTwoWeekLowChangePercent": 0.15861103, "fiftyTwoWeekRange": "319.65 - 622.0", "fiftyTwoWeekHighChange": -251.65, "fiftyTwoWeekHighChangePercent": -0.404582, "fiftyTwoWeekChangePercent": 13.840878, "earningsTimestampStart": 1754909940, "earningsTimestampEnd": 1755259200, "isEarningsDateEstimate": true, "epsTrailingTwelveMonths": 32.51, "fiftyDayAverageChange": -50.017, "fiftyDayAverageChangePercent": -0.11898412, "twoHundredDayAverageChange": -122.254486, "twoHundredDayAverageChangePercent": -0.24817981, "sourceInterval": 15, "exchangeDataDelayedBy": 15, "marketState": "REGULAR", "cryptoTradeable": false, "trailingPegRatio": null}