{"address1": "Time Tower", "address2": "4th Floor Unit No. 408, MG Road", "city": "Gurugram", "zip": "122002", "country": "India", "phone": "91 12 4694 9200", "website": "https://www.pinelabs.com", "industry": "Software - Infrastructure", "industryKey": "software-infrastructure", "industryDisp": "Software - Infrastructure", "sector": "Technology", "sectorKey": "technology", "sectorDisp": "Technology", "longBusinessSummary": "Pine Labs Limited, a technology company, provides digital payments and issuing solutions for merchants, consumer brands and enterprises, and financial institutions in India, Malaysia, the United Arab Emirates, Singapore, Australia, the United States, and Africa. It operates through Digital Infrastructure and Transaction Platform, and Issuing and Acquiring Platform segments. The Digital Infrastructure and Transaction Platform segment provides technology platforms under the brand name of Pinelabs, Mosambee, Benow, Setu, Qfix, and Fave to merchants that enables acceptance of instore or online digital payments. These technology platforms and infrastructure allow merchants to accept debit cards, credit cards, prepaid instruments wallets, QR codes, unified payment interface, loyalty points, pay later, online fee collection, etc., as well as provide application programming interface modules to customers for building financial products that facilitates bill payments, credit, and savings to enable purchases made by consumers. It also engages in selling digital checkout points devices. The Issuing and Acquiring Platform segment provides a technology platform to issue, process, and distribute prepaid cards primarily in India and South East Asia. It also monetizes primarily by charging a processing fee from merchants who are utilizing the technology platform and in the case of distribution. The company was incorporated in 1998 and is based in Gurugram, India.", "fullTimeEmployees": 4231, "companyOfficers": [{"maxAge": 1, "name": "Mr. Neerav  Mehta", "title": "Company Secretary & Compliance Officer", "exercisedValue": 0, "unexercisedValue": 0}, {"maxAge": 1, "name": "Ms. Vijayalakshmi  Swaminathan", "title": "Chief People Officer", "exercisedValue": 0, "unexercisedValue": 0}, {"maxAge": 1, "name": "Mr. Kush  Mehra", "age": 44, "title": "President, CBO of Digital Infrastructure & Transaction platform and Whole-Time Director", "yearBorn": 1981, "exercisedValue": 0, "unexercisedValue": 0}, {"maxAge": 1, "name": "Mr. Sanjeev  Kumar", "title": "Chief Technology Officer of Digital Infrastructure & Transaction Platform", "exercisedValue": 0, "unexercisedValue": 0}, {"maxAge": 1, "name": "Mr. Sameer  Maheshwary", "title": "Chief Capital Markets Officer", "exercisedValue": 0, "unexercisedValue": 0}, {"maxAge": 1, "name": "Mr. Navin Ashok Kumar Chandani", "title": "President & Chief Business Officer of Issuing Business", "exercisedValue": 0, "unexercisedValue": 0}, {"maxAge": 1, "name": "Mr. Sumit  Chopra", "title": "Chief Operating Officer of Digital Infrastructure & Transaction Platform", "exercisedValue": 0, "unexercisedValue": 0}, {"maxAge": 1, "name": "Mr. Anand  Raisinghani", "title": "President & Chief Business Officer of Setu", "exercisedValue": 0, "unexercisedValue": 0}, {"maxAge": 1, "name": "Mr. Bairavarasu Amrish Rau", "age": 52, "title": "MD, CEO & Chairman", "yearBorn": 1973, "exercisedValue": 0, "unexercisedValue": 0}, {"maxAge": 1, "name": "Mr. Lokvir  Kapoor", "title": "Co-Founder", "exercisedValue": 0, "unexercisedValue": 0}], "executiveTeam": [], "maxAge": 86400, "priceHint": 2, "previousClose": 168.27, "open": 168.27, "dayLow": 163.41, "dayHigh": 172.9, "regularMarketPreviousClose": 168.27, "regularMarketOpen": 168.27, "regularMarketDayLow": 163.41, "regularMarketDayHigh": 172.9, "payoutRatio": 0.0, "trailingPE": 783.1905, "forwardPE": 53.725365, "volume": 854196, "regularMarketVolume": 854196, "averageVolume": 1276067, "averageVolume10days": 624365, "averageDailyVolume10Day": 624365, "bid": 164.47, "ask": 0.0, "marketCap": 188857008128, "nonDilutedMarketCap": 188857015725, "fiftyTwoWeekLow": 158.42, "fiftyTwoWeekHigh": 284.0, "allTimeHigh": 284.0, "allTimeLow": 158.42, "priceToSalesTrailing12Months": 7.23944, "fiftyDayAverage": 203.764, "twoHundredDayAverage": 219.31935, "trailingAnnualDividendRate": 0.0, "trailingAnnualDividendYield": 0.0, "currency": "INR", "tradeable": false, "enterpriseValue": 131415416832, "profitMargins": 0.00929, "floatShares": 569509650, "sharesOutstanding": 1148276377, "heldPercentInsiders": 0.0060799997, "heldPercentInstitutions": 0.16055, "impliedSharesOutstanding": 1148276377, "bookValue": 37.293, "priceToBook": 4.410211, "lastFiscalYearEnd": 1743379200, "nextFiscalYearEnd": 1774915200, "mostRecentQuarter": 1767139200, "netIncomeToCommon": 242430000, "trailingEps": 0.21, "forwardEps": 3.06131, "enterpriseToRevenue": 5.038, "enterpriseToEbitda": 28.668, "52WeekChange": -0.34445375, "SandP52WeekChange": 0.12811458, "quoteType": "EQUITY", "currentPrice": 164.47, "targetHighPrice": 300.0, "targetLowPrice": 225.0, "targetMeanPrice": 258.75, "targetMedianPrice": 255.0, "recommendationMean": 2.25, "recommendationKey": "buy", "numberOfAnalystOpinions": 4, "totalCash": 60637298688, "totalCashPerShare": 54.358, "ebitda": 4584110080, "totalDebt": 8582099968, "totalRevenue": 26087239680, "debtToEquity": 23.128, "revenuePerShare": 25.205, "grossProfits": 8937029632, "revenueGrowth": 0.237, "grossMargins": 0.34258, "ebitdaMargins": 0.17572, "operatingMargins": 0.08708999, "financialCurrency": "INR", "symbol": "PINELABS.NS", "language": "en-US", "region": "US", "typeDisp": "Equity", "quoteSourceName": "Delayed Quote", "triggerable": true, "customPriceAlertConfidence": "HIGH", "hasPrePostMarketData": false, "firstTradeDateMilliseconds": 1763091900000, "regularMarketChange": -3.800003, "regularMarketDayRange": "163.41 - 172.9", "fullExchangeName": "NSE", "averageDailyVolume3Month": 1276067, "fiftyTwoWeekLowChange": 6.050003, "fiftyTwoWeekLowChangePercent": 0.038189642, "fiftyTwoWeekRange": "158.42 - 284.0", "fiftyTwoWeekHighChange": -119.53, "fiftyTwoWeekHighChangePercent": -0.4208803, "fiftyTwoWeekChangePercent": -34.445374, "epsTrailingTwelveMonths": 0.21, "epsForward": 3.06131, "epsCurrentYear": 1.11784, "marketState": "CLOSED", "regularMarketChangePercent": -2.2582772, "regularMarketPrice": 164.47, "shortName": "PINE LABS LIMITED", "priceEpsCurrentYear": 147.13196, "fiftyDayAverageChange": -39.294006, "fiftyDayAverageChangePercent": -0.19284075, "twoHundredDayAverageChange": -54.84935, "twoHundredDayAverageChangePercent": -0.25008896, "sourceInterval": 15, "exchangeDataDelayedBy": 15, "averageAnalystRating": "2.3 - Buy", "cryptoTradeable": false, "corporateActions": [], "regularMarketTime": 1774000803, "exchange": "NSI", "messageBoardId": "finmb_100763821", "exchangeTimezoneName": "Asia/Kolkata", "exchangeTimezoneShortName": "IST", "gmtOffSetMilliseconds": 19800000, "market": "in_market", "esgPopulated": false, "trailingPegRatio": null}