{"address1": "Ambuja Tower", "address2": "Opp. Sindhu Bhavan, Sindhu Bhavan Road Bodakdev P.O. Thaltej", "city": "Ahmedabad", "zip": "380054", "country": "India", "phone": "91 79 6155 6677", "fax": "91 79 6155 6678", "website": "https://www.ambujagroup.com", "industry": "Packaged Foods", "industryKey": "packaged-foods", "industryDisp": "Packaged Foods", "sector": "Consumer Defensive", "sectorKey": "consumer-defensive", "sectorDisp": "Consumer Defensive", "longBusinessSummary": "Gujarat Ambuja Exports Limited primarily engages in the agro processing activities in India and internationally. It operates through the Agro, Spinning, Maize, and Power segments. The company offers starch derivatives, including maize starch, liquid glucose, dextrose monohydrate powder, maltodextrin, sorbitol 70% solution, dextrose anhydrous powder, pregelatinized starch, maltitol syrup, glucose syrup solids, high maltose corn syrup and dextrose syrup; soya derivatives that consist of defatted soya flour/flakes/grits, full fat soya flour/flakes/grits, liquid soya lecithin, and soya granules and soya nuggets; feed ingredients, such as corn gluten meal, cattle feed, rapeseed extraction meal, soybean meal, maize germ, corn steep liquor, maize fiber, and CSL fiber; edible oils, which include filtered groundnut, filtered mustard, refined corn, refined cotton seed, refined palm, refined soybean, and refined sunflower oils; and agro based products comprising bakery shortening, Vanaspati ghee, and wheat flour. The company also manufactures cotton and polyester yarn. In addition, it operates windmills with a capacity of 10 megawatts, solar plants with a capacity of 10 megawatts, biogas engines with a capacity of 8 megawatts, and rice husk boilers with a capacity of 16 megawatts. The company serves the pharmaceuticals, confectionery, bakery, animal feed, paint, baby food, cosmetic, toothpaste, paper, edible oil, textile, and industrial adhesive industries. Gujarat Ambuja Exports Limited was founded in 1986 and is based in Ahmedabad, India.", "fullTimeEmployees": 2351, "companyOfficers": [{"maxAge": 1, "name": "Mr. Manish Vijaykumar Gupta", "age": 53, "title": "MD & Chairman", "yearBorn": 1972, "fiscalYear": 2025, "totalPay": 378200000, "exercisedValue": 0, "unexercisedValue": 0}, {"maxAge": 1, "name": "Mr. Giridhar  Nagaraj", "age": 66, "title": "Chief Financial Officer", "yearBorn": 1959, "fiscalYear": 2025, "exercisedValue": 0, "unexercisedValue": 0}, {"maxAge": 1, "name": "Mr. Kalpesh Bhupatbhai Dave", "age": 35, "title": "Company Secretary & Compliance Officer", "yearBorn": 1990, "fiscalYear": 2025, "exercisedValue": 0, "unexercisedValue": 0}, {"maxAge": 1, "name": "Mr. Sandeep N. Agrawal", "age": 54, "title": "Whole Time Director", "yearBorn": 1971, "fiscalYear": 2025, "totalPay": 8500000, "exercisedValue": 0, "unexercisedValue": 0}, {"maxAge": 1, "name": "Mr. Brijmohan  Chitlange", "title": "President", "fiscalYear": 2025, "exercisedValue": 0, "unexercisedValue": 0}, {"maxAge": 1, "name": "Mr. Basu  Tibrewala", "title": "Chief Executive", "fiscalYear": 2025, "exercisedValue": 0, "unexercisedValue": 0}, {"maxAge": 1, "name": "Mr. Shreyaan Manish Gupta", "title": "Additional Whole-Time Director", "fiscalYear": 2025, "exercisedValue": 0, "unexercisedValue": 0}], "compensationAsOfEpochDate": 1767139200, "executiveTeam": [], "maxAge": 86400, "priceHint": 2, "previousClose": 130.2, "open": 129.3, "dayLow": 126.45, "dayHigh": 129.53, "regularMarketPreviousClose": 130.2, "regularMarketOpen": 129.3, "regularMarketDayLow": 126.45, "regularMarketDayHigh": 129.53, "dividendRate": 0.25, "dividendYield": 0.19, "exDividendDate": 1755820800, "payoutRatio": 0.0571, "fiveYearAvgDividendYield": 2.98, "beta": -0.214, "trailingPE": 29.189932, "forwardPE": 13.716128, "volume": 80847, "regularMarketVolume": 80847, "averageVolume": 1091972, "averageVolume10days": 550338, "averageDailyVolume10Day": 550338, "bid": 127.76, "ask": 127.95, "bidSize": 0, "askSize": 0, "marketCap": 58508025856, "nonDilutedMarketCap": 59695986399, "fiftyTwoWeekLow": 100.5, "fiftyTwoWeekHigh": 149.11, "allTimeHigh": 210.6, "allTimeLow": 0.375, "priceToSalesTrailing12Months": 1.0582582, "fiftyDayAverage": 137.2592, "twoHundredDayAverage": 117.3719, "trailingAnnualDividendRate": 0.0, "trailingAnnualDividendYield": 0.0, "currency": "INR", "tradeable": false, "enterpriseValue": 54889566208, "profitMargins": 0.03633, "floatShares": 135955422, "sharesOutstanding": 458670660, "heldPercentInsiders": 0.70302004, "heldPercentInstitutions": 0.01127, "impliedSharesOutstanding": 458670660, "bookValue": 67.527, "priceToBook": 1.8890221, "lastFiscalYearEnd": 1743379200, "nextFiscalYearEnd": 1774915200, "mostRecentQuarter": 1767139200, "earningsQuarterlyGrowth": -0.077, "netIncomeToCommon": 2008600064, "trailingEps": 4.37, "forwardEps": 9.3, "lastSplitFactor": "2:1", "lastSplitDate": 1710460800, "enterpriseToRevenue": 0.993, "enterpriseToEbitda": 16.32, "52WeekChange": 0.26727664, "SandP52WeekChange": 0.16864312, "lastDividendValue": 0.25, "lastDividendDate": 1755820800, "quoteType": "EQUITY", "currentPrice": 127.56, "targetHighPrice": 138.0, "targetLowPrice": 138.0, "targetMeanPrice": 138.0, "targetMedianPrice": 138.0, "recommendationKey": "none", "numberOfAnalystOpinions": 1, "totalCash": 7596199936, "totalCashPerShare": 16.594, "ebitda": 3363300096, "totalDebt": 2883099904, "totalRevenue": 55287099392, "debtToEquity": 9.321, "revenuePerShare": 120.448, "grossProfits": 12632699904, "earningsGrowth": -0.077, "revenueGrowth": 0.312, "grossMargins": 0.22849001, "ebitdaMargins": 0.06083, "operatingMargins": 0.04448, "financialCurrency": "INR", "symbol": "GAEL.NS", "language": "en-US", "region": "US", "typeDisp": "Equity", "quoteSourceName": "Free Realtime Quote", "triggerable": true, "customPriceAlertConfidence": "HIGH", "hasPrePostMarketData": false, "firstTradeDateMilliseconds": 1025495100000, "corporateActions": [], "regularMarketTime": 1773633107, "exchange": "NSI", "messageBoardId": "finmb_9454988", "exchangeTimezoneName": "Asia/Kolkata", "exchangeTimezoneShortName": "IST", "gmtOffSetMilliseconds": 19800000, "market": "in_market", "esgPopulated": false, "regularMarketChangePercent": -2.0254714, "regularMarketPrice": 127.56, "regularMarketChange": -2.6399994, "regularMarketDayRange": "126.45 - 129.53", "fullExchangeName": "NSE", "averageDailyVolume3Month": 1091972, "fiftyTwoWeekLowChange": 27.059998, "fiftyTwoWeekLowChangePercent": 0.2692537, "fiftyTwoWeekRange": "100.5 - 149.11", "fiftyTwoWeekHighChange": -21.550003, "fiftyTwoWeekHighChangePercent": -0.1445242, "fiftyTwoWeekChangePercent": 26.727665, "earningsTimestampStart": 1754045940, "earningsTimestampEnd": 1754395200, "isEarningsDateEstimate": true, "epsTrailingTwelveMonths": 4.37, "epsForward": 9.3, "epsCurrentYear": 4.4, "priceEpsCurrentYear": 28.990908, "fiftyDayAverageChange": -9.6992035, "fiftyDayAverageChangePercent": -0.070663415, "twoHundredDayAverageChange": 10.188095, "twoHundredDayAverageChangePercent": 0.08680182, "sourceInterval": 15, "exchangeDataDelayedBy": 15, "cryptoTradeable": false, "marketState": "REGULAR", "shortName": "GUJARAT AMBUJA EXPORTS LT", "longName": "Gujarat Ambuja Exports Limited", "trailingPegRatio": null}