{"address1": "10th Floor Tower B", "address2": "Paras Twin Towers Sector-54 Golf Course Road", "city": "Gurugram", "zip": "122 002", "country": "India", "phone": "91 12 4478 4530", "website": "https://www.tennecoindia.com", "industry": "Auto Parts", "industryKey": "auto-parts", "industryDisp": "Auto Parts", "sector": "Consumer Cyclical", "sectorKey": "consumer-cyclical", "sectorDisp": "Consumer Cyclical", "longBusinessSummary": "Tenneco Clean Air India Limited operates as a manufacturer and supplier of clean air and powertrain solutions. The company operates in two segments, clean air and powertrain solutions; and advanced ride technologies. The company designs, manufactures, and sells exhaust aftertreatment systems, such as catalytic converters, mufflers, and exhaust pipes; engine bearings, sealing systems, and ignition products, such as spark plugs and ignition coils; and shock absorbers, struts, and suspension systems. Its products are used in passenger vehicles, commercial trucks, off-highway vehicles, generator sets, small commercial vehicles, two wheelers and three wheelers. Tenneco Clean Air India Limited was founded in 1979 and is based in Gurugram, India. Tenneco Clean Air India Limited operates as a subsidiary of Tenneco Mauritius Holdings Limited.", "fullTimeEmployees": 1992, "companyOfficers": [{"maxAge": 1, "name": "Mr. Arvind  Chandrasekharan", "age": 55, "title": "CEO & Whole-Time Director", "yearBorn": 1970, "exercisedValue": 0, "unexercisedValue": 0}, {"maxAge": 1, "name": "Mr. Mahender  Chhabra", "title": "Chief Financial Officer", "exercisedValue": 0, "unexercisedValue": 0}, {"maxAge": 1, "name": "Ms. Roopali  Singh", "title": "General Counsel, Company Secretary & Compliance Officer", "exercisedValue": 0, "unexercisedValue": 0}, {"maxAge": 1, "name": "Mr. Rishi  Verma", "age": 45, "title": "President of India", "yearBorn": 1980, "exercisedValue": 0, "unexercisedValue": 0}], "executiveTeam": [], "maxAge": 86400, "priceHint": 2, "previousClose": 546.5, "open": 540.0, "dayLow": 535.15, "dayHigh": 541.4, "regularMarketPreviousClose": 546.5, "regularMarketOpen": 540.0, "regularMarketDayLow": 535.15, "regularMarketDayHigh": 541.4, "payoutRatio": 0.0, "trailingPE": 37.479053, "forwardPE": 31.324911, "volume": 43532, "regularMarketVolume": 43532, "averageVolume": 865939, "averageVolume10days": 446040, "averageDailyVolume10Day": 446040, "bid": 536.9, "ask": 537.1, "nonDilutedMarketCap": 220569754868, "fiftyTwoWeekLow": 438.05, "fiftyTwoWeekHigh": 602.0, "allTimeHigh": 602.0, "allTimeLow": 438.05, "fiftyDayAverage": 541.044, "twoHundredDayAverage": 520.4455, "trailingAnnualDividendRate": 0.0, "trailingAnnualDividendYield": 0.0, "currency": "INR", "tradeable": false, "enterpriseValue": 217196888064, "profitMargins": 0.11146, "floatShares": 101789089, "heldPercentInsiders": 0.0, "heldPercentInstitutions": 0.11733, "bookValue": 22.737, "priceToBook": 23.604698, "lastFiscalYearEnd": 1743379200, "nextFiscalYearEnd": 1774915200, "mostRecentQuarter": 1767139200, "earningsQuarterlyGrowth": -0.052, "netIncomeToCommon": 5771449856, "trailingEps": 14.32, "forwardEps": 17.13333, "enterpriseToRevenue": 4.195, "enterpriseToEbitda": 24.664, "52WeekChange": 0.1134882, "SandP52WeekChange": 0.12811458, "quoteType": "EQUITY", "currentPrice": 536.7, "targetHighPrice": 650.0, "targetLowPrice": 429.0, "targetMeanPrice": 573.0, "targetMedianPrice": 640.0, "recommendationKey": "none", "numberOfAnalystOpinions": 3, "totalCash": 3678990080, "totalCashPerShare": 9.113, "ebitda": 8806127616, "totalDebt": 225150000, "totalRevenue": 51778191360, "debtToEquity": 2.447, "revenuePerShare": 128.274, "grossProfits": 17719539712, "earningsGrowth": -0.052, "revenueGrowth": 0.142, "grossMargins": 0.34222, "ebitdaMargins": 0.17006999, "operatingMargins": 0.1511, "financialCurrency": "INR", "symbol": "TENNIND.NS", "language": "en-US", "region": "US", "typeDisp": "Equity", "quoteSourceName": "Free Realtime Quote", "triggerable": true, "customPriceAlertConfidence": "HIGH", "hasPrePostMarketData": false, "firstTradeDateMilliseconds": 1763523900000, "regularMarketChange": -9.799988, "regularMarketDayRange": "535.15 - 541.4", "fullExchangeName": "NSE", "averageDailyVolume3Month": 865939, "fiftyTwoWeekLowChange": 98.650024, "fiftyTwoWeekLowChangePercent": 0.22520266, "fiftyTwoWeekRange": "438.05 - 602.0", "fiftyTwoWeekHighChange": -65.29999, "fiftyTwoWeekHighChangePercent": -0.108471744, "fiftyTwoWeekChangePercent": 11.34882, "epsTrailingTwelveMonths": 14.32, "epsForward": 17.13333, "epsCurrentYear": 15.4, "marketState": "REGULAR", "regularMarketChangePercent": -1.791916, "regularMarketPrice": 536.7, "shortName": "TENNECO CLEAN AIR INDIA L", "priceEpsCurrentYear": 34.85065, "fiftyDayAverageChange": -4.343994, "fiftyDayAverageChangePercent": -0.0080289105, "twoHundredDayAverageChange": 16.254517, "twoHundredDayAverageChangePercent": 0.031231929, "sourceInterval": 15, "exchangeDataDelayedBy": 15, "cryptoTradeable": false, "corporateActions": [], "regularMarketTime": 1774239908, "exchange": "NSI", "messageBoardId": "finmb_717634524", "exchangeTimezoneName": "Asia/Kolkata", "exchangeTimezoneShortName": "IST", "gmtOffSetMilliseconds": 19800000, "market": "in_market", "esgPopulated": false, "trailingPegRatio": null}