{"address1": "Apollo House, 7", "address2": "Institutional Area Sector-32", "city": "Gurugram", "zip": "122001", "country": "India", "phone": "91 12 4238 3002", "fax": "91 12 4238 3021", "website": "https://www.ptlenterprise.com", "industry": "Real Estate Services", "industryKey": "real-estate-services", "industryDisp": "Real Estate Services", "sector": "Real Estate", "sectorKey": "real-estate", "sectorDisp": "Real Estate", "longBusinessSummary": "PTL Enterprises Limited engages in the lease of plant to Apollo Tyres Limited. The company was formerly known as Premier Tyres Ltd. PTL Enterprises Limited is based in Gurugram, India. PTL Enterprises Limited is a subsidiary of Sunrays Properties & Investment Co. Pvt. Ltd.", "fullTimeEmployees": 574, "companyOfficers": [{"maxAge": 1, "name": "Mr. Amarjeet  Kumar", "age": 41, "title": "Chief Financial Officer", "yearBorn": 1984, "fiscalYear": 2025, "totalPay": 3299000, "exercisedValue": 0, "unexercisedValue": 0}, {"maxAge": 1, "name": "Ms. Jyoti  Upmanyu", "title": "Company Secretary & Compliance Officer", "fiscalYear": 2025, "totalPay": 1268000, "exercisedValue": 0, "unexercisedValue": 0}], "compensationAsOfEpochDate": 1767139200, "executiveTeam": [], "maxAge": 86400, "priceHint": 2, "previousClose": 37.37, "open": 37.45, "dayLow": 37.45, "dayHigh": 38.05, "regularMarketPreviousClose": 37.37, "regularMarketOpen": 37.45, "regularMarketDayLow": 37.45, "regularMarketDayHigh": 38.05, "dividendRate": 3.25, "dividendYield": 8.62, "exDividendDate": 1770681600, "payoutRatio": 0.5556, "fiveYearAvgDividendYield": 5.36, "beta": -0.093, "trailingPE": 11.965078, "forwardPE": 6.453767, "volume": 9804, "regularMarketVolume": 9804, "averageVolume": 63082, "averageVolume10days": 40456, "averageDailyVolume10Day": 40456, "bid": 0.0, "ask": 0.0, "bidSize": 0, "askSize": 0, "marketCap": 4989288960, "nonDilutedMarketCap": 4977375200, "fiftyTwoWeekLow": 36.0, "fiftyTwoWeekHigh": 47.4, "allTimeHigh": 89.0, "allTimeLow": 3.175, "priceToSalesTrailing12Months": 7.754435, "fiftyDayAverage": 38.8508, "twoHundredDayAverage": 40.01755, "trailingAnnualDividendRate": 0.0, "trailingAnnualDividendYield": 0.0, "currency": "INR", "tradeable": false, "enterpriseValue": 5106880000, "profitMargins": 0.64778, "floatShares": 28830454, "sharesOutstanding": 132377000, "heldPercentInsiders": 0.78363997, "heldPercentInstitutions": 0.0, "impliedSharesOutstanding": 132377000, "bookValue": 67.848, "priceToBook": 0.5555064, "lastFiscalYearEnd": 1743379200, "nextFiscalYearEnd": 1774915200, "mostRecentQuarter": 1767139200, "earningsQuarterlyGrowth": 0.062, "netIncomeToCommon": 416788992, "trailingEps": 3.15, "forwardEps": 5.84, "lastSplitFactor": "2:1", "lastSplitDate": 1640217600, "enterpriseToRevenue": 7.937, "enterpriseToEbitda": 8.76, "52WeekChange": -0.05515164, "SandP52WeekChange": 0.12811458, "lastDividendValue": 1.5, "lastDividendDate": 1770681600, "quoteType": "EQUITY", "currentPrice": 37.69, "recommendationKey": "none", "totalCash": 8154000, "totalCashPerShare": 0.061, "ebitda": 582979776, "totalDebt": 92757000, "totalRevenue": 643411008, "debtToEquity": 1.036, "revenuePerShare": 4.865, "grossProfits": 643278976, "earningsGrowth": 0.063, "revenueGrowth": 0.0, "grossMargins": 0.99978995, "ebitdaMargins": 0.90608, "operatingMargins": 0.86127, "financialCurrency": "INR", "symbol": "PTL.NS", "language": "en-US", "region": "US", "typeDisp": "Equity", "quoteSourceName": "Delayed Quote", "triggerable": true, "customPriceAlertConfidence": "HIGH", "longName": "PTL Enterprises Limited", "marketState": "CLOSED", "shortName": "PTL ENTERPRISES LTD", "hasPrePostMarketData": false, "firstTradeDateMilliseconds": 1170042300000, "regularMarketChange": 0.3199997, "regularMarketDayRange": "37.45 - 38.05", "fullExchangeName": "NSE", "averageDailyVolume3Month": 63082, "fiftyTwoWeekLowChange": 1.6899986, "fiftyTwoWeekLowChangePercent": 0.046944406, "fiftyTwoWeekRange": "36.0 - 47.4", "fiftyTwoWeekHighChange": -9.710003, "fiftyTwoWeekHighChangePercent": -0.20485237, "fiftyTwoWeekChangePercent": -5.5151644, "earningsTimestampStart": 1754391540, "earningsTimestampEnd": 1754740800, "isEarningsDateEstimate": true, "epsTrailingTwelveMonths": 3.15, "epsForward": 5.84, "fiftyDayAverageChange": -1.1608009, "fiftyDayAverageChangePercent": -0.02987843, "twoHundredDayAverageChange": -2.3275528, "twoHundredDayAverageChangePercent": -0.0581633, "sourceInterval": 15, "exchangeDataDelayedBy": 15, "corporateActions": [], "regularMarketTime": 1774000794, "exchange": "NSI", "messageBoardId": "finmb_20358475", "exchangeTimezoneName": "Asia/Kolkata", "exchangeTimezoneShortName": "IST", "gmtOffSetMilliseconds": 19800000, "market": "in_market", "esgPopulated": false, "regularMarketChangePercent": 0.85630107, "regularMarketPrice": 37.69, "cryptoTradeable": false, "trailingPegRatio": null}