{"address1": "# 7-1-19/3, I.S.R. Complex", "address2": "1st Floor Kundanbagh Begumpet, Telangana", "city": "Hyderabad", "zip": "500016", "country": "India", "phone": "91 40 4026 6333", "website": "https://www.countrycondos.co.in", "industry": "Real Estate - Development", "industryKey": "real-estate-development", "industryDisp": "Real Estate - Development", "sector": "Real Estate", "sectorKey": "real-estate", "sectorDisp": "Real Estate", "longBusinessSummary": "Country Condo's Limited engages in the real estate business in India. The company procures land banks; develops residential layouts; constructs compound walls; and sells plots. It also provides contract research services. The company was formerly known as Neocure Therapeutics Ltd. and changed its name to Country Condo's Limited in December 2006. Country Condo's Limited was incorporated in 1987 and is headquartered in Hyderabad, India.", "fullTimeEmployees": 79, "companyOfficers": [{"maxAge": 1, "name": "Mr. Datla Krishna Kumar Raju", "age": 68, "title": "Executive Vice-Chairman & CEO", "yearBorn": 1957, "fiscalYear": 2025, "totalPay": 4290000, "exercisedValue": 0, "unexercisedValue": 0}, {"maxAge": 1, "name": "Mr. Upputuri  Gandhi", "title": "Chief Financial Officer", "fiscalYear": 2025, "exercisedValue": 0, "unexercisedValue": 0}, {"maxAge": 1, "name": "Mr. Laxmikanth  Jakhotia", "title": "Chief Compliance Officer & Company Secretary", "fiscalYear": 2025, "exercisedValue": 0, "unexercisedValue": 0}], "compensationAsOfEpochDate": 1767139200, "executiveTeam": [], "maxAge": 86400, "priceHint": 2, "previousClose": 4.84, "open": 4.95, "dayLow": 4.71, "dayHigh": 5.03, "regularMarketPreviousClose": 4.84, "regularMarketOpen": 4.95, "regularMarketDayLow": 4.71, "regularMarketDayHigh": 5.03, "payoutRatio": 0.0, "beta": 0.135, "trailingPE": 71.571434, "volume": 3709, "regularMarketVolume": 3709, "averageVolume": 92400, "averageVolume10days": 124780, "averageDailyVolume10Day": 124780, "bid": 4.81, "ask": 5.01, "bidSize": 0, "askSize": 0, "marketCap": 388762464, "nonDilutedMarketCap": 370915094, "fiftyTwoWeekLow": 4.52, "fiftyTwoWeekHigh": 11.92, "allTimeHigh": 11.92, "allTimeLow": 0.183333, "priceToSalesTrailing12Months": 2.3670964, "fiftyDayAverage": 5.2634, "twoHundredDayAverage": 6.2986, "trailingAnnualDividendRate": 0.0, "trailingAnnualDividendYield": 0.0, "currency": "INR", "tradeable": false, "enterpriseValue": 325566016, "profitMargins": 0.03066, "floatShares": 28507088, "sharesOutstanding": 77597300, "heldPercentInsiders": 0.58247, "heldPercentInstitutions": 0.0, "impliedSharesOutstanding": 77597300, "bookValue": 3.698, "priceToBook": 1.3547864, "lastFiscalYearEnd": 1743379200, "nextFiscalYearEnd": 1774915200, "mostRecentQuarter": 1767139200, "earningsQuarterlyGrowth": -0.542, "netIncomeToCommon": 5036000, "trailingEps": 0.07, "lastSplitFactor": "3:1", "lastSplitDate": 1252022400, "enterpriseToRevenue": 1.982, "enterpriseToEbitda": 37.434, "52WeekChange": -0.13105923, "SandP52WeekChange": 0.16864312, "quoteType": "EQUITY", "currentPrice": 5.01, "recommendationKey": "none", "totalCash": 9237000, "totalCashPerShare": 0.134, "ebitda": 8697000, "totalDebt": 117000, "totalRevenue": 164236000, "debtToEquity": 0.046, "revenuePerShare": 2.191, "grossProfits": 116279000, "earningsGrowth": -0.667, "revenueGrowth": -0.096, "grossMargins": 0.708, "ebitdaMargins": 0.052950002, "operatingMargins": 0.022219999, "financialCurrency": "INR", "symbol": "COUNCODOS.NS", "language": "en-US", "region": "US", "typeDisp": "Equity", "quoteSourceName": "Free Realtime Quote", "triggerable": true, "customPriceAlertConfidence": "HIGH", "corporateActions": [], "regularMarketTime": 1773632955, "exchange": "NSI", "messageBoardId": "finmb_20950892", "exchangeTimezoneName": "Asia/Kolkata", "exchangeTimezoneShortName": "IST", "gmtOffSetMilliseconds": 19800000, "market": "in_market", "esgPopulated": false, "regularMarketChangePercent": 3.5123982, "regularMarketPrice": 5.01, "hasPrePostMarketData": false, "firstTradeDateMilliseconds": 1025495100000, "marketState": "REGULAR", "regularMarketChange": 0.17000008, "regularMarketDayRange": "4.71 - 5.03", "fullExchangeName": "NSE", "averageDailyVolume3Month": 92400, "fiftyTwoWeekLowChange": 0.49000025, "fiftyTwoWeekLowChangePercent": 0.10840713, "fiftyTwoWeekRange": "4.52 - 11.92", "fiftyTwoWeekHighChange": -6.91, "fiftyTwoWeekHighChangePercent": -0.57969797, "fiftyTwoWeekChangePercent": -13.105923, "epsTrailingTwelveMonths": 0.07, "fiftyDayAverageChange": -0.25339985, "fiftyDayAverageChangePercent": -0.048143756, "twoHundredDayAverageChange": -1.2886, "twoHundredDayAverageChangePercent": -0.20458513, "sourceInterval": 15, "exchangeDataDelayedBy": 15, "cryptoTradeable": false, "shortName": "COUNTRY CONDO S LIMITED", "longName": "Country Condo's Limited", "trailingPegRatio": null}