{"address1": "125, Kandivli Industrial Estate", "address2": "Kandivli (West)", "city": "Mumbai", "zip": "400067", "country": "India", "phone": "91 22 6210 5000", "fax": "91 22 6210 5439", "website": "https://www.ipca.com", "industry": "Drug Manufacturers - Specialty & Generic", "industryKey": "drug-manufacturers-specialty-generic", "industryDisp": "Drug Manufacturers - Specialty & Generic", "sector": "Healthcare", "sectorKey": "healthcare", "sectorDisp": "Healthcare", "longBusinessSummary": "Ipca Laboratories Limited, an integrated pharmaceutical company, manufactures and markets formulations and active pharmaceutical ingredients (APIs) for various therapeutic segments in India, Europe, Africa, the Americas, Asia, the Commonwealth of Independent States, and Australasia. The company offers APIs in anti-hypertensive, anti-malarial, diuretic, DMARD, anti-hypertensive, and anthelmintic therapeutic areas. It also provides generic and branded formulations in various therapeutic segments, including allergy, anti-neoplastic/cancer drugs, anti-arthritic, anti-epileptic, anti-hypertensive, cardiology, diabetes, dermatology, diabetology, emollients/protectives, fever, gastroenterology, helminthics, hepatoprotectives, immunosuppressant, infectious diseases, malaria, neurology, neuropathic pain, and NSAIDs, as well as nutraceuticals, ophthalmology, oral anti diabetes drug, orthopedics, probiotics, psychiatry, respiratory, rheumatology, and urology. The company also exports its products worldwide. Ipca Laboratories Limited was incorporated in 1949 and is based in Mumbai, India.", "fullTimeEmployees": 16778, "companyOfficers": [{"maxAge": 1, "name": "Mr. Premchand  Godha A.C. A., B. Com., CA", "age": 78, "title": "Executive Chairman", "yearBorn": 1947, "fiscalYear": 2025, "totalPay": 135194180, "exercisedValue": 0, "unexercisedValue": 0}, {"maxAge": 1, "name": "Mr. Pranay Premchand Godha", "age": 53, "title": "CEO, MD & Executive Director", "yearBorn": 1972, "fiscalYear": 2025, "totalPay": 89750783, "exercisedValue": 0, "unexercisedValue": 0}, {"maxAge": 1, "name": "Mr. Ajit Kumar Bhanwarlal Jain A.C.A., B.Sc.", "age": 70, "title": "CFO, MD & Executive Director", "yearBorn": 1955, "fiscalYear": 2025, "totalPay": 97673498, "exercisedValue": 0, "unexercisedValue": 0}, {"maxAge": 1, "name": "Mr. Prashant Premchand Godha", "age": 51, "title": "Executive Director", "yearBorn": 1974, "fiscalYear": 2025, "totalPay": 69975716, "exercisedValue": 0, "unexercisedValue": 0}, {"maxAge": 1, "name": "Mr. Pawan  Kothari", "age": 60, "title": "Vice President of Operations", "yearBorn": 1965, "fiscalYear": 2025, "exercisedValue": 0, "unexercisedValue": 0}, {"maxAge": 1, "name": "Mr. Vishnu Saran Singh Kushwaha", "age": 57, "title": "Vice President of Technical", "yearBorn": 1968, "fiscalYear": 2025, "exercisedValue": 0, "unexercisedValue": 0}, {"maxAge": 1, "name": "Mr. Harish Pandurang Kamath", "age": 66, "title": "Compliance Officer, Corporate Counsel & Company Secretary", "yearBorn": 1959, "fiscalYear": 2025, "exercisedValue": 0, "unexercisedValue": 0}, {"maxAge": 1, "name": "Mr. Sunil  Ghai", "age": 62, "title": "President of Marketing", "yearBorn": 1963, "fiscalYear": 2025, "exercisedValue": 0, "unexercisedValue": 0}, {"maxAge": 1, "name": "Mr. Saidutta  Nanda", "title": "President of Human Resources", "fiscalYear": 2025, "exercisedValue": 0, "unexercisedValue": 0}, {"maxAge": 1, "name": "Dr. Ashok  Kumar", "age": 71, "title": "President of R&D - Chemicals", "yearBorn": 1954, "fiscalYear": 2025, "exercisedValue": 0, "unexercisedValue": 0}], "compensationAsOfEpochDate": 1767139200, "executiveTeam": [], "maxAge": 86400, "priceHint": 2, "previousClose": 1561.3, "open": 1565.6, "dayLow": 1546.1, "dayHigh": 1568.8, "regularMarketPreviousClose": 1561.3, "regularMarketOpen": 1565.6, "regularMarketDayLow": 1546.1, "regularMarketDayHigh": 1568.8, "dividendRate": 4.0, "dividendYield": 0.26, "exDividendDate": 1754352000, "payoutRatio": 0.0558, "fiveYearAvgDividendYield": 0.35, "beta": 0.211, "trailingPE": 43.177387, "forwardPE": 28.730003, "volume": 14878, "regularMarketVolume": 14878, "averageVolume": 206952, "averageVolume10days": 170969, "averageDailyVolume10Day": 170969, "bid": 1548.6, "ask": 1550.5, "bidSize": 0, "askSize": 0, "marketCap": 394796138496, "nonDilutedMarketCap": 395981543454, "fiftyTwoWeekLow": 1168.2, "fiftyTwoWeekHigh": 1595.0, "allTimeHigh": 1755.9, "allTimeLow": 2.75, "priceToSalesTrailing12Months": 4.153052, "fiftyDayAverage": 1481.94, "twoHundredDayAverage": 1408.618, "trailingAnnualDividendRate": 2.0, "trailingAnnualDividendYield": 0.0012809838, "currency": "INR", "tradeable": false, "enterpriseValue": 435972964352, "profitMargins": 0.09571, "floatShares": 148181633, "sharesOutstanding": 253704218, "heldPercentInsiders": 0.45082, "heldPercentInstitutions": 0.46605998, "impliedSharesOutstanding": 254625056, "bookValue": 324.6, "priceToBook": 4.776648, "lastFiscalYearEnd": 1743379200, "nextFiscalYearEnd": 1774915200, "mostRecentQuarter": 1767139200, "earningsQuarterlyGrowth": 0.315, "netIncomeToCommon": 9098699776, "trailingEps": 35.91, "forwardEps": 53.96797, "lastSplitFactor": "2:1", "lastSplitDate": 1641772800, "enterpriseToRevenue": 4.586, "enterpriseToEbitda": 23.21, "52WeekChange": 0.18486762, "SandP52WeekChange": 0.16864312, "lastDividendValue": 2.0, "lastDividendDate": 1754352000, "quoteType": "EQUITY", "currentPrice": 1550.5, "targetHighPrice": 1800.0, "targetLowPrice": 1350.0, "targetMeanPrice": 1649.7778, "targetMedianPrice": 1689.0, "recommendationMean": 1.76471, "recommendationKey": "buy", "numberOfAnalystOpinions": 18, "totalCash": 12549799936, "totalCashPerShare": 46.504, "ebitda": 18783899648, "totalDebt": 12789199872, "totalRevenue": 95061696512, "debtToEquity": 14.425, "revenuePerShare": 378.441, "grossProfits": 63638798336, "earningsGrowth": 0.236, "revenueGrowth": 0.066, "grossMargins": 0.66945, "ebitdaMargins": 0.1976, "operatingMargins": 0.17796, "financialCurrency": "INR", "symbol": "IPCALAB.NS", "language": "en-US", "region": "US", "typeDisp": "Equity", "quoteSourceName": "Free Realtime Quote", "triggerable": true, "customPriceAlertConfidence": "HIGH", "hasPrePostMarketData": false, "firstTradeDateMilliseconds": 820467900000, "corporateActions": [], "regularMarketTime": 1773633239, "exchange": "NSI", "messageBoardId": "finmb_4481217", "exchangeTimezoneName": "Asia/Kolkata", "exchangeTimezoneShortName": "IST", "gmtOffSetMilliseconds": 19800000, "market": "in_market", "esgPopulated": false, "regularMarketChangePercent": -0.6927993, "regularMarketPrice": 1550.5, "regularMarketChange": -10.800049, "regularMarketDayRange": "1546.1 - 1568.8", "fullExchangeName": "NSE", "averageDailyVolume3Month": 206952, "fiftyTwoWeekLowChange": 382.30005, "fiftyTwoWeekLowChangePercent": 0.32725567, "fiftyTwoWeekRange": "1168.2 - 1595.0", "fiftyTwoWeekHighChange": -44.5, "fiftyTwoWeekHighChangePercent": -0.027899686, "fiftyTwoWeekChangePercent": 18.486763, "earningsTimestamp": 1770976800, "earningsTimestampStart": 1770976800, "earningsTimestampEnd": 1770976800, "earningsCallTimestampStart": 1771236000, "earningsCallTimestampEnd": 1771236000, "isEarningsDateEstimate": false, "epsTrailingTwelveMonths": 35.91, "epsForward": 53.96797, "epsCurrentYear": 45.13222, "priceEpsCurrentYear": 34.354614, "fiftyDayAverageChange": 68.56006, "fiftyDayAverageChangePercent": 0.046263725, "twoHundredDayAverageChange": 141.88196, "twoHundredDayAverageChangePercent": 0.10072422, "sourceInterval": 15, "exchangeDataDelayedBy": 15, "averageAnalystRating": "1.8 - Buy", "cryptoTradeable": false, "marketState": "REGULAR", "shortName": "IPCA LABORATORIES LTD", "longName": "Ipca Laboratories Limited", "trailingPegRatio": null}